[{"text": "387 376", "x0": 487, "y0": 127, "x1": 607, "y1": 240, "rotation": -0.8645304165147882}, {"text": "more have metro systems approved. As of 2020, China boasts the five longest metro systems in the world with the networks in Shanghai, Beijing, Guangzhou, Chengdu and Shenzhen being the largest. There were approximately 229 airports in 2017, with around 240 planned by 2020. China has over 2,000 river and seaports, about 130 of which are open to foreign shipping. In 2017, the Ports of Shanghai, Hong Kong, Shenzhen, Ningbo-Zhoushan, Guangzhou, Qingdao and Tianjin ranked in the Top 10 in the world in container traffic and cargo tonnage. Water supply and sanitation infrastructure in China is facing challenges such as rapid urbanization, as well as water scarcity, contamination, and", "x0": 328, "y0": 415, "x1": 710, "y1": 722}, {"text": "German war machine. By October 1944, the Soviets had reached the river Tisza, and despite some losses, succeeded in encircling and besieging Budapest in December. After German occupation, Hungary participated in", "x0": 68, "y0": 286, "x1": 237, "y1": 718}]