[{"text": "398,768", "x0": 624, "y0": 798, "x1": 744, "y1": 911, "rotation": -1.3397147291653129}, {"text": "debated, but some of them possibly date from 2nd millennium BC. Other prehistoric sites of somewhat uncertain date are Samrong Sen (not far from the ancient capital of Oudong), where the first investigations began in 1875, and Phum Snay, in the northern province of Banteay Meanchey. An excavation at Phum Snay revealed 21 graves with iron weapons and cranial trauma which could point to conflicts in the past, possible with larger cities in Angkor. Prehistoric artefacts are often found during mining activities in Ratanakiri.Iron was worked by", "x0": 228, "y0": 571, "x1": 496, "y1": 1027}, {"text": "increase during the 18th and 19th centuries, which the writer Esaias Tegnér in 1833 attributed to \"the peace, the smallpox vaccine, and the potatoes\". Between 1750 and 1850, the population in Sweden doubled. According to some scholars, mass emigration to America became the only way to prevent famine and", "x0": 181, "y0": 137, "x1": 447, "y1": 460}]